ts/__init__.py
ts/auth.py
ts/color.py
ts/config.py
ts/core.py
ts/httpclient.py
ts/log.py
ts/utils.py
ts-0.5.1.dist-info/METADATA
ts-0.5.1.dist-info/RECORD
ts-0.5.1.dist-info/WHEEL
ts-0.5.1.dist-info/entry_points.txt
ts-0.5.1.dist-info/top_level.txt
