Metadata-Version: 2.1
Name: ts
Version: 0.5.1
Summary: Twitter Search CLI
Home-page: https://github.com/reorx/ts
Author: reorx
Author-email: novoreorx@gmail.com
License: UNKNOWN
Platform: UNKNOWN
Requires-Dist: requests
Requires-Dist: requests-oauthlib
Requires-Dist: python-dateutil
Requires-Dist: six
